[
  {
    "line": 3,
    "elements": [
      {
        "comments": [
          {
            "line": 5,
            "value": "#Tests As a business, I should be able to post a job to the job portal"
          },
          {
            "line": 6,
            "value": "#"
          },
          {
            "line": 7,
            "value": "#Acceptance Criteria"
          },
          {
            "line": 8,
            "value": "#"
          },
          {
            "line": 9,
            "value": "## A business which wants to post a job must have a registered/approved account"
          },
          {
            "line": 10,
            "value": "## User must be logged-in"
          },
          {
            "line": 11,
            "value": "## User clicks on the Add a Job button from Job Portal on the navigation panel and one-page loads with the following fields"
          },
          {
            "line": 12,
            "value": "### Job Category (industry)"
          },
          {
            "line": 13,
            "value": "### Job Type (Full/part-time, contract, daily job, etc)"
          },
          {
            "line": 14,
            "value": "### Job Location"
          },
          {
            "line": 15,
            "value": "### Job Title"
          },
          {
            "line": 16,
            "value": "### Job description (Responsibilities \u0026 Requirements)"
          },
          {
            "line": 17,
            "value": "### Salary range (two fields: From, To)"
          },
          {
            "line": 18,
            "value": "### Job Ad Expiry Date"
          },
          {
            "line": 19,
            "value": "#"
          },
          {
            "line": 20,
            "value": "#4. User click on the Save button and it is recorded in the database"
          }
        ],
        "before": [
          {
            "result": {
              "duration": 6742880000,
              "status": "passed"
            },
            "match": {
              "location": "Addjobs_steps.setup()"
            }
          }
        ],
        "line": 22,
        "name": "Verify that an organisation user can add a job",
        "description": "",
        "id": "job-portal;verify-that-an-organisation-user-can-add-a-job",
        "after": [
          {
            "result": {
              "duration": 674961900,
              "status": "passed"
            },
            "match": {
              "location": "Addjobs_steps.end()"
            }
          }
        ],
        "type": "scenario",
        "keyword": "Scenario",
        "steps": [
          {
            "result": {
              "duration": 2500260000,
              "status": "passed"
            },
            "line": 23,
            "name": "user enters the platform",
            "match": {
              "location": "Addjobs_steps.user_enters_the_platform()"
            },
            "keyword": "When "
          },
          {
            "result": {
              "duration": 87300,
              "status": "passed"
            },
            "line": 24,
            "name": "user selects add job",
            "match": {
              "location": "Addjobs_steps.user_selects_add_job()"
            },
            "keyword": "And "
          },
          {
            "result": {
              "duration": 874232700,
              "error_message": "org.openqa.selenium.ElementNotInteractableException: element not interactable\n  (Session info: chrome\u003d86.0.4240.111)\nBuild info: version: \u00273.141.59\u0027, revision: \u0027e82be7d358\u0027, time: \u00272018-11-14T08:17:03\u0027\nSystem info: host: \u0027DESKTOP-6APU30H\u0027, ip: \u0027192.168.1.188\u0027, os.name: \u0027Windows 10\u0027, os.arch: \u0027amd64\u0027, os.version: \u002710.0\u0027, java.version: \u00271.8.0_202\u0027\nDriver info: org.openqa.selenium.chrome.ChromeDriver\nCapabilities {acceptInsecureCerts: false, browserName: chrome, browserVersion: 86.0.4240.111, chrome: {chromedriverVersion: 86.0.4240.22 (398b0743353ff..., userDataDir: C:\\Users\\USER\\AppData\\Local...}, goog:chromeOptions: {debuggerAddress: localhost:60115}, javascriptEnabled: true, networkConnectionEnabled: false, pageLoadStrategy: normal, platform: WINDOWS, platformName: WINDOWS, proxy: Proxy(), setWindowRect: true, strictFileInteractability: false, timeouts: {implicit: 0, pageLoad: 300000, script: 30000}, unhandledPromptBehavior: dismiss and notify, webauthn:virtualAuthenticators: true}\nSession ID: ab31c27608ca36c98747705731ddaeaf\r\n\tat sun.reflect.NativeConstructorAccessorImpl.newInstance0(Native Method)\r\n\tat sun.reflect.NativeConstructorAccessorImpl.newInstance(NativeConstructorAccessorImpl.java:62)\r\n\tat sun.reflect.DelegatingConstructorAccessorImpl.newInstance(DelegatingConstructorAccessorImpl.java:45)\r\n\tat java.lang.reflect.Constructor.newInstance(Constructor.java:423)\r\n\tat org.openqa.selenium.remote.http.W3CHttpResponseCodec.createException(W3CHttpResponseCodec.java:187)\r\n\tat org.openqa.selenium.remote.http.W3CHttpResponseCodec.decode(W3CHttpResponseCodec.java:122)\r\n\tat org.openqa.selenium.remote.http.W3CHttpResponseCodec.decode(W3CHttpResponseCodec.java:49)\r\n\tat org.openqa.selenium.remote.HttpCommandExecutor.execute(HttpCommandExecutor.java:158)\r\n\tat org.openqa.selenium.remote.service.DriverCommandExecutor.execute(DriverCommandExecutor.java:83)\r\n\tat org.openqa.selenium.remote.RemoteWebDriver.execute(RemoteWebDriver.java:552)\r\n\tat org.openqa.selenium.remote.RemoteWebElement.execute(RemoteWebElement.java:285)\r\n\tat org.openqa.selenium.remote.RemoteWebElement.sendKeys(RemoteWebElement.java:106)\r\n\tat steps.Addjobs_steps.user_completes_all_fields(Addjobs_steps.java:73)\r\n\tat ✽.And user completes all fields(F:/Add_Job/AddJob/src/test/java/AddJob/add_Job.feature:25)\r\n",
              "status": "failed"
            },
            "line": 25,
            "name": "user completes all fields",
            "match": {
              "location": "Addjobs_steps.user_completes_all_fields()"
            },
            "keyword": "And "
          },
          {
            "result": {
              "status": "skipped"
            },
            "line": 26,
            "name": "user clicks post",
            "match": {
              "location": "Addjobs_steps.user_clicks_post()"
            },
            "keyword": "When "
          },
          {
            "result": {
              "status": "skipped"
            },
            "line": 27,
            "name": "user should receive a notification of success",
            "match": {
              "location": "Addjobs_steps.user_should_receive_a_notification_of_success()"
            },
            "keyword": "Then "
          }
        ],
        "tags": [
          {
            "line": 21,
            "name": "@TEST_COMMUNITY-744"
          },
          {
            "line": 21,
            "name": "@REQ_COMMUNITY-21"
          },
          {
            "line": 21,
            "name": "@TESTSET_COMMUNITY-708"
          }
        ]
      }
    ],
    "name": "Job portal",
    "description": "",
    "id": "job-portal",
    "keyword": "Feature",
    "uri": "F:/Add_Job/AddJob/src/test/java/AddJob/add_Job.feature",
    "tags": [
      {
        "line": 1,
        "name": "@COMMUNITY-713"
      },
      {
        "line": 2,
        "name": "@REQ_COMMUNITY-6"
      }
    ]
  }
]